{
  "debug": {
    "build": {
      "compileArgs": [
        "-DIDF_TARGET=esp32s3"
      ],
      "ninjaArgs": [],
      "buildDirectoryPath": "${workspaceFolder}/build/debug",
      "sdkconfigDefaults": [
        "${workspaceFolder}/sdkconfig.common",
        "${workspaceFolder}/sdkconfig.debug"
      ],
      "sdkconfigFilePath": "${workspaceFolder}/build/sdkconfig.debug"
    },
    "env": {},
    "idfTarget": "esp32s3",
    "flashBaudRate": "",
    "monitorBaudRate": "",
    "openOCD": {
      "debugLevel": 4,
      "configs": [],
      "args": []
    },
    "tasks": {
      "preBuild": "",
      "preFlash": "",
      "postBuild": "",
      "postFlash": ""
    }
  },
  "debug-mockADC": {
    "build": {
      "compileArgs": [
        "-DIDF_TARGET=esp32s3"
      ],
      "ninjaArgs": [],
      "buildDirectoryPath": "${workspaceFolder}/build/debug-mockadc",
      "sdkconfigDefaults": [
        "${workspaceFolder}/sdkconfig.common",
        "${workspaceFolder}/sdkconfig.debug",
        "${workspaceFolder}/sdkconfig.debug-mockadc"
      ],
      "sdkconfigFilePath": "${workspaceFolder}/build/sdkconfig.debug-mockadc"
    },
    "env": {},
    "flashBaudRate": "",
    "monitorBaudRate": "",
    "openOCD": {
      "debugLevel": 4,
      "configs": [],
      "args": []
    },
    "tasks": {
      "preBuild": "",
      "preFlash": "",
      "postBuild": "",
      "postFlash": ""
    }
  },
  "release": {
    "build": {
      "compileArgs": [],
      "ninjaArgs": [],
      "buildDirectoryPath": "${workspaceFolder}/build/release",
      "sdkconfigDefaults": [
        "${workspaceFolder}/sdkconfig.common",
        "${workspaceFolder}/sdkconfig.release"
      ],
      "sdkconfigFilePath": "${workspaceFolder}/build/sdkconfig.release"
    },
    "env": {},
    "flashBaudRate": "",
    "monitorBaudRate": "",
    "openOCD": {
      "debugLevel": 4,
      "configs": [],
      "args": []
    },
    "tasks": {
      "preBuild": "",
      "preFlash": "",
      "postBuild": "",
      "postFlash": ""
    }
  }
}